kotify.fabric-0.20.0-py3.8-nspkg.pth
kotify/fabric/__init__.py
kotify/fabric/_config.py
kotify/fabric/_core.py
kotify/fabric/aws.py
kotify/fabric/database.py
kotify/fabric/deploy.py
kotify/fabric/docker.py
kotify/fabric/procfile.py
kotify/fabric/ssh.py
kotify/fabric/start.py
kotify.fabric-0.20.0.dist-info/LICENSE
kotify.fabric-0.20.0.dist-info/METADATA
kotify.fabric-0.20.0.dist-info/WHEEL
kotify.fabric-0.20.0.dist-info/namespace_packages.txt
kotify.fabric-0.20.0.dist-info/top_level.txt
kotify.fabric-0.20.0.dist-info/RECORD
