Metadata-Version: 2.1
Name: kotify.fabric
Version: 0.20.0
Summary: Fabric helpers library
Home-page: https://github.com/kotify/kotify.fabric
Author: Konstantin Alekseev
Author-email: konstantin@kotify.com
License: MIT License
Platform: UNKNOWN
Classifier: Development Status :: 5 - Production/Stable
Classifier: Environment :: Web Environment
Classifier: Intended Audience :: Developers
Classifier: License :: OSI Approved :: MIT License
Classifier: Operating System :: OS Independent
Classifier: Programming Language :: Python
Classifier: Programming Language :: Python :: 3
Classifier: Programming Language :: Python :: 3.6
Classifier: Programming Language :: Python :: 3.7
Classifier: Programming Language :: Python :: 3.8
Classifier: Topic :: Software Development :: Libraries :: Python Modules
Requires-Python: >=3.6
Requires-Dist: fabric (<3.0,>=2.5.0)
Requires-Dist: paramiko (<3.0,>=2.7.0)
